{
    "bed_0": {
        "confidence": 0.8528491854667664,
        "class": "bed",
        "bbox": [
            413.2391357421875,
            526.9542236328125,
            1179.8525390625,
            988.283935546875
        ]
    },
    "potted plant_1": {
        "confidence": 0.7801806926727295,
        "class": "potted plant",
        "bbox": [
            1017.1268310546875,
            515.0,
            1135.0831298828125,
            633.2504272460938
        ]
    },
    "vase_2": {
        "confidence": 0.2796461582183838,
        "class": "vase",
        "bbox": [
            1048.4052734375,
            588.4216918945312,
            1107.07373046875,
            632.3095092773438
        ]
    }
}